setup.cfg
setup.py
awsbb.egg-info/PKG-INFO
awsbb.egg-info/SOURCES.txt
awsbb.egg-info/dependency_links.txt
awsbb.egg-info/entry_points.txt
awsbb.egg-info/requires.txt
awsbb.egg-info/top_level.txt
awsbigbrother/__init__.py
awsbigbrother/action.py
awsbigbrother/cli.py
awsbigbrother/client.py
awsbigbrother/config.py
awsbigbrother/report.py
test/test_cli.py
test/test_client.py
test/test_report.py